{"version":1,"resource":"file:///home/sebastianr/github.com/sebastianromero/go/src/patriciomorales/veterinariamovil/layouts/index.html","entries":[{"id":"yBaH.html","timestamp":1699142732765},{"id":"meqK.html","timestamp":1699142758759},{"id":"dwGS.html","timestamp":1699142874555},{"id":"Tnom.html","timestamp":1699143003725},{"id":"lJRQ.html","timestamp":1699143037182},{"id":"ZWAv.html","timestamp":1699143399249},{"id":"qRb9.html","timestamp":1699144099545},{"id":"EbCj.html","timestamp":1699144196025},{"id":"hcke.html","timestamp":1699144330015},{"id":"NLc4.html","timestamp":1699144387555},{"id":"D46P.html","timestamp":1699144467929},{"id":"ocKa.html","source":"undoRedo.source","timestamp":1699144508162},{"id":"0jcM.html","timestamp":1699144597529},{"id":"GgoQ.html","timestamp":1699144657055},{"id":"cciG.html","timestamp":1699145111489},{"id":"vKzF.html","timestamp":1699302941481},{"id":"SrtB.html","timestamp":1699304087778},{"id":"oIa9.html","timestamp":1699304846828},{"id":"F0k6.html","timestamp":1699305045165},{"id":"wL63.html","source":"undoRedo.source","timestamp":1699305127192},{"id":"di3H.html","timestamp":1699305497952},{"id":"lPTX.html","timestamp":1699305626442},{"id":"rHGW.html","timestamp":1699305677622},{"id":"y7eh.html","timestamp":1699305745152},{"id":"AE5W.html","timestamp":1699305941732},{"id":"xn1V.html","timestamp":1699305959045},{"id":"MmZn.html","timestamp":1699306203892},{"id":"pnay.html","timestamp":1699306277118},{"id":"Y1Yx.html","timestamp":1699306396085},{"id":"36vr.html","timestamp":1699306423358},{"id":"OuIl.html","timestamp":1699306591478},{"id":"xJmo.html","timestamp":1699306746195},{"id":"bxbP.html","timestamp":1699306818252},{"id":"1hkI.html","timestamp":1699306997298},{"id":"aLmp.html","timestamp":1699307062302},{"id":"OZE1.html","timestamp":1699307115595},{"id":"ZXSY.html","timestamp":1699307194388},{"id":"7Uor.html","timestamp":1699307767962},{"id":"VfcX.html","timestamp":1699307841008},{"id":"F6zb.html","timestamp":1699307926765},{"id":"Jw4E.html","timestamp":1699307988278},{"id":"zvpm.html","timestamp":1699308211692},{"id":"REgM.html","timestamp":1699308272882},{"id":"RQHC.html","timestamp":1699308319205},{"id":"0Fje.html","source":"undoRedo.source","timestamp":1699308524318},{"id":"bHfY.html","timestamp":1699310843115},{"id":"Cs6P.html","timestamp":1699311239472},{"id":"KBQF.html","timestamp":1699908498298},{"id":"IdYd.html","timestamp":1699924518860},{"id":"xLze.html","timestamp":1700604157039}]}